{
  "codigo": "1.05.2.003",
  "categoria": "Medicina Interna",
  "categoria_id": "01",
  "subcategoria": "Enfermedades respiratorias",
  "subcategoria_id": "05",
  "nombre_tema": null,
  "tipo": "Urgencia",
  "total_preguntas": 20,
  "preguntas": [
    {
      "numero": "1",
      "texto": "¿Qué caracteriza a la aspiración de cuerpo extraño sin asfixia?",
      "alternativas": [
        {
          "opcion": "A",
          "texto": "Obstrucción completa de la vía aérea superior"
        },
        {
          "opcion": "B",
          "texto": "Aspiración parcial con ventilación conservada"
        },
        {
          "opcion": "C",
          "texto": "Paro cardiorrespiratorio inmediato"
        },
        {
          "opcion": "D",
          "texto": "Hipoxia severa con cianosis generalizada"
        },
        {
          "opcion": "E",
          "texto": "Ausencia de reflejo tusígeno"
        }
      ],
      "respuesta_correcta": "B",
      "explicacion": "En la aspiración sin asfixia la obstrucción es parcial, permitiendo ventilación y oxigenación adecuadas."
    },
    {
      "numero": "2",
      "texto": "¿Cuál es el síntoma más frecuente en la aspiración de cuerpo extraño sin asfixia?",
      "alternativas": [
        {
          "opcion": "A",
          "texto": "Tos persistente"
        },
        {
          "opcion": "B",
          "texto": "Disnea intensa"
        },
        {
          "opcion": "C",
          "texto": "Cianosis"
        },
        {
          "opcion": "D",
          "texto": "Apnea súbita"
        },
        {
          "opcion": "E",
          "texto": "Dolor torácico agudo"
        }
      ],
      "respuesta_correcta": "A",
      "explicacion": "La tos persistente es el síntoma más común en aspiración sin obstrucción completa."
    },
    {
      "numero": "3",
      "texto": "¿Qué hallazgo auscultatorio sugiere la presencia de un cuerpo extraño bronquial?",
      "alternativas": [
        {
          "opcion": "A",
          "texto": "Murmullo vesicular aumentado"
        },
        {
          "opcion": "B",
          "texto": "Sibilancias localizadas"
        },
        {
          "opcion": "C",
          "texto": "Estertores crepitantes bilaterales"
        },
        {
          "opcion": "D",
          "texto": "Roncus difusos"
        },
        {
          "opcion": "E",
          "texto": "Silencio auscultatorio bilateral"
        }
      ],
      "respuesta_correcta": "B",
      "explicacion": "Las sibilancias localizadas son típicas de una obstrucción bronquial parcial por cuerpo extraño."
    },
    {
      "numero": "4",
      "texto": "¿Cuál es el sitio más común de impactación en la aspiración sin asfixia?",
      "alternativas": [
        {
          "opcion": "A",
          "texto": "Tráquea"
        },
        {
          "opcion": "B",
          "texto": "Bronquio principal derecho"
        },
        {
          "opcion": "C",
          "texto": "Bronquio principal izquierdo"
        },
        {
          "opcion": "D",
          "texto": "Laringe"
        },
        {
          "opcion": "E",
          "texto": "Bronquiolos terminales"
        }
      ],
      "respuesta_correcta": "B",
      "explicacion": "El bronquio derecho es más vertical y ancho, por lo que es el sitio más frecuente de impactación."
    },
    {
      "numero": "5",
      "texto": "¿Cuál es el estudio de elección para confirmar la aspiración de cuerpo extraño?",
      "alternativas": [
        {
          "opcion": "A",
          "texto": "Radiografía de tórax posteroanterior y lateral"
        },
        {
          "opcion": "B",
          "texto": "Ecografía torácica"
        },
        {
          "opcion": "C",
          "texto": "Broncoscopía"
        },
        {
          "opcion": "D",
          "texto": "Gasometría arterial"
        },
        {
          "opcion": "E",
          "texto": "Tomografía de cráneo"
        }
      ],
      "respuesta_correcta": "C",
      "explicacion": "La broncoscopía permite visualizar directamente y extraer el cuerpo extraño aspirado."
    },
    {
      "numero": "6",
      "texto": "En la radiografía, la hiperclaridad pulmonar unilateral sugiere:",
      "alternativas": [
        {
          "opcion": "A",
          "texto": "Derrame pleural"
        },
        {
          "opcion": "B",
          "texto": "Atrapamiento aéreo por efecto valvular"
        },
        {
          "opcion": "C",
          "texto": "Neumotórax"
        },
        {
          "opcion": "D",
          "texto": "Atelectasia"
        },
        {
          "opcion": "E",
          "texto": "Fibrosis pulmonar"
        }
      ],
      "respuesta_correcta": "B",
      "explicacion": "La obstrucción parcial actúa como válvula, atrapando aire distalmente y generando hiperclaridad unilateral."
    },
    {
      "numero": "7",
      "texto": "¿Qué característica clínica diferencia una aspiración sin asfixia de una con asfixia?",
      "alternativas": [
        {
          "opcion": "A",
          "texto": "Tos débil y cianosis leve"
        },
        {
          "opcion": "B",
          "texto": "Presencia de tos efectiva y ventilación conservada"
        },
        {
          "opcion": "C",
          "texto": "Afonía súbita y apnea"
        },
        {
          "opcion": "D",
          "texto": "Colapso circulatorio"
        },
        {
          "opcion": "E",
          "texto": "Estridor grave"
        }
      ],
      "respuesta_correcta": "B",
      "explicacion": "La tos efectiva y el mantenimiento de la ventilación distinguen la aspiración sin asfixia."
    },
    {
      "numero": "8",
      "texto": "¿Qué complicación puede desarrollarse si el cuerpo extraño no se extrae oportunamente?",
      "alternativas": [
        {
          "opcion": "A",
          "texto": "Bronquiectasias localizadas"
        },
        {
          "opcion": "B",
          "texto": "Hipertensión pulmonar"
        },
        {
          "opcion": "C",
          "texto": "Embolia pulmonar"
        },
        {
          "opcion": "D",
          "texto": "Edema agudo de pulmón"
        },
        {
          "opcion": "E",
          "texto": "Fibrosis intersticial difusa"
        }
      ],
      "respuesta_correcta": "A",
      "explicacion": "La retención crónica del cuerpo extraño puede causar inflamación y bronquiectasias en el área afectada."
    },
    {
      "numero": "9",
      "texto": "El síntoma más frecuente en aspiración crónica no diagnosticada es:",
      "alternativas": [
        {
          "opcion": "A",
          "texto": "Fiebre alta"
        },
        {
          "opcion": "B",
          "texto": "Tos persistente y localizada"
        },
        {
          "opcion": "C",
          "texto": "Hemoptisis masiva"
        },
        {
          "opcion": "D",
          "texto": "Dolor torácico punzante"
        },
        {
          "opcion": "E",
          "texto": "Taquipnea severa"
        }
      ],
      "respuesta_correcta": "B",
      "explicacion": "La tos crónica localizada es típica en aspiraciones no diagnosticadas durante semanas o meses."
    },
    {
      "numero": "10",
      "texto": "En adultos, el tipo de material aspirado más común es:",
      "alternativas": [
        {
          "opcion": "A",
          "texto": "Monedas"
        },
        {
          "opcion": "B",
          "texto": "Fragmentos dentales o de alimento"
        },
        {
          "opcion": "C",
          "texto": "Juguetes plásticos"
        },
        {
          "opcion": "D",
          "texto": "Pequeñas semillas"
        },
        {
          "opcion": "E",
          "texto": "Material metálico"
        }
      ],
      "respuesta_correcta": "B",
      "explicacion": "En adultos, los alimentos sólidos o fragmentos dentales son los más comúnmente aspirados."
    },
    {
      "numero": "11",
      "texto": "En un paciente con sibilancias unilaterales persistentes, se debe sospechar:",
      "alternativas": [
        {
          "opcion": "A",
          "texto": "Asma bronquial"
        },
        {
          "opcion": "B",
          "texto": "Aspiración de cuerpo extraño"
        },
        {
          "opcion": "C",
          "texto": "EPOC"
        },
        {
          "opcion": "D",
          "texto": "Neumonía viral"
        },
        {
          "opcion": "E",
          "texto": "Fibrosis quística"
        }
      ],
      "respuesta_correcta": "B",
      "explicacion": "Las sibilancias unilaterales persistentes son indicativas de posible cuerpo extraño bronquial."
    },
    {
      "numero": "12",
      "texto": "¿Qué hallazgo radiográfico puede observarse en la expiración en aspiración parcial?",
      "alternativas": [
        {
          "opcion": "A",
          "texto": "Atelectasia bilateral"
        },
        {
          "opcion": "B",
          "texto": "Hiperclaridad persistente del hemitórax afectado"
        },
        {
          "opcion": "C",
          "texto": "Infiltrados alveolares difusos"
        },
        {
          "opcion": "D",
          "texto": "Neumotórax apical"
        },
        {
          "opcion": "E",
          "texto": "Broncograma aéreo"
        }
      ],
      "respuesta_correcta": "B",
      "explicacion": "La hiperclaridad en espiración indica atrapamiento de aire por obstrucción parcial."
    },
    {
      "numero": "13",
      "texto": "¿Cuál es la herramienta diagnóstica de mayor sensibilidad en la aspiración sin asfixia?",
      "alternativas": [
        {
          "opcion": "A",
          "texto": "Radiografía simple"
        },
        {
          "opcion": "B",
          "texto": "Tomografía computarizada de tórax"
        },
        {
          "opcion": "C",
          "texto": "Broncoscopía flexible"
        },
        {
          "opcion": "D",
          "texto": "Gasometría arterial"
        },
        {
          "opcion": "E",
          "texto": "Espirometría"
        }
      ],
      "respuesta_correcta": "C",
      "explicacion": "La broncoscopía flexible permite visualizar el cuerpo extraño y realizar extracción si es necesario."
    },
    {
      "numero": "14",
      "texto": "El signo de Chevalier Jackson se asocia a:",
      "alternativas": [
        {
          "opcion": "A",
          "texto": "Movimiento del cuerpo extraño con la respiración"
        },
        {
          "opcion": "B",
          "texto": "Hipertrofia bronquial crónica"
        },
        {
          "opcion": "C",
          "texto": "Hemoptisis masiva"
        },
        {
          "opcion": "D",
          "texto": "Edema laríngeo progresivo"
        },
        {
          "opcion": "E",
          "texto": "Vasoconstricción pulmonar reflejada"
        }
      ],
      "respuesta_correcta": "A",
      "explicacion": "El signo de Chevalier Jackson describe el movimiento del cuerpo extraño con la respiración o tos."
    },
    {
      "numero": "15",
      "texto": "¿Qué tipo de cuerpo extraño es más difícil de detectar por radiografía?",
      "alternativas": [
        {
          "opcion": "A",
          "texto": "Metal"
        },
        {
          "opcion": "B",
          "texto": "Plástico o alimento vegetal"
        },
        {
          "opcion": "C",
          "texto": "Vidrio"
        },
        {
          "opcion": "D",
          "texto": "Hueso calcificado"
        },
        {
          "opcion": "E",
          "texto": "Prótesis dental metálica"
        }
      ],
      "respuesta_correcta": "B",
      "explicacion": "Los objetos radiolúcidos como alimentos o plásticos no se visualizan fácilmente en la radiografía."
    },
    {
      "numero": "16",
      "texto": "En un paciente pediátrico, la aspiración sin asfixia suele manifestarse con:",
      "alternativas": [
        {
          "opcion": "A",
          "texto": "Afonía súbita y apnea"
        },
        {
          "opcion": "B",
          "texto": "Tos intermitente, fiebre y sibilancias unilaterales"
        },
        {
          "opcion": "C",
          "texto": "Taquicardia sinusal sostenida"
        },
        {
          "opcion": "D",
          "texto": "Hipotensión arterial"
        },
        {
          "opcion": "E",
          "texto": "Edema facial"
        }
      ],
      "respuesta_correcta": "B",
      "explicacion": "La tos intermitente y las sibilancias unilaterales en un niño sugieren aspiración parcial no diagnosticada."
    },
    {
      "numero": "17",
      "texto": "El tratamiento de elección para la extracción de cuerpo extraño en vías aéreas inferiores es:",
      "alternativas": [
        {
          "opcion": "A",
          "texto": "Broncoscopía rígida"
        },
        {
          "opcion": "B",
          "texto": "Fisioterapia respiratoria"
        },
        {
          "opcion": "C",
          "texto": "Intubación orotraqueal profunda"
        },
        {
          "opcion": "D",
          "texto": "Antibióticos profilácticos"
        },
        {
          "opcion": "E",
          "texto": "Lavado bronquial con suero fisiológico"
        }
      ],
      "respuesta_correcta": "A",
      "explicacion": "La broncoscopía rígida es el procedimiento más eficaz y seguro para extracción de cuerpos extraños traqueobronquiales."
    },
    {
      "numero": "18",
      "texto": "¿Cuál es la complicación infecciosa más común tras aspiración sin extracción inmediata?",
      "alternativas": [
        {
          "opcion": "A",
          "texto": "Neumonía obstructiva"
        },
        {
          "opcion": "B",
          "texto": "Empiema pleural"
        },
        {
          "opcion": "C",
          "texto": "Tuberculosis secundaria"
        },
        {
          "opcion": "D",
          "texto": "Absceso hepático"
        },
        {
          "opcion": "E",
          "texto": "Sinusitis crónica"
        }
      ],
      "respuesta_correcta": "A",
      "explicacion": "El cuerpo extraño puede causar neumonía obstructiva por estasis y colonización bacteriana distal."
    },
    {
      "numero": "19",
      "texto": "En la aspiración sin asfixia, el tratamiento antibiótico profiláctico está indicado:",
      "alternativas": [
        {
          "opcion": "A",
          "texto": "Siempre tras extracción del cuerpo extraño"
        },
        {
          "opcion": "B",
          "texto": "Solo si hay signos de infección o neumonía"
        },
        {
          "opcion": "C",
          "texto": "En todos los pacientes pediátricos"
        },
        {
          "opcion": "D",
          "texto": "Antes de realizar broncoscopía"
        },
        {
          "opcion": "E",
          "texto": "En pacientes asintomáticos"
        }
      ],
      "respuesta_correcta": "B",
      "explicacion": "El antibiótico se indica únicamente si hay evidencia clínica o radiológica de infección respiratoria."
    },
    {
      "numero": "20",
      "texto": "¿Qué hallazgo radiológico indica resolución tras la extracción del cuerpo extraño?",
      "alternativas": [
        {
          "opcion": "A",
          "texto": "Persistencia de hiperinsuflación"
        },
        {
          "opcion": "B",
          "texto": "Reexpansión pulmonar y normalización del parénquima"
        },
        {
          "opcion": "C",
          "texto": "Infiltrado alveolar bilateral"
        },
        {
          "opcion": "D",
          "texto": "Atelectasia residual"
        },
        {
          "opcion": "E",
          "texto": "Desviación traqueal persistente"
        }
      ],
      "respuesta_correcta": "B",
      "explicacion": "La reexpansión pulmonar y la desaparición de hiperclaridad confirman la resolución postextracción."
    }
  ]
}