{
  "codigo": "2.01.1.139",
  "categoria": "Pediatria",
  "categoria_id": "02",
  "subcategoria": "Trastornos de alimentación",
  "subcategoria_id": "00",
  "nombre_tema": null,
  "tipo": "Crónico",
  "total_preguntas": 19,
  "preguntas": [
    {
      "numero": "1",
      "texto": "¿Cuál de los siguientes trastornos de alimentación se caracteriza por restricción calórica y miedo intenso a ganar peso?",
      "alternativas": [
        {
          "opcion": "A",
          "texto": "Bulimia nerviosa"
        },
        {
          "opcion": "B",
          "texto": "Trastorno por atracón"
        },
        {
          "opcion": "C",
          "texto": "Anorexia nerviosa"
        },
        {
          "opcion": "D",
          "texto": "Pica"
        },
        {
          "opcion": "E",
          "texto": "Rumicación"
        }
      ],
      "respuesta_correcta": "C",
      "explicacion": "La anorexia nerviosa se caracteriza por restricción de la ingesta, bajo peso y miedo patológico a engordar."
    },
    {
      "numero": "2",
      "texto": "¿Cuál es una complicación frecuente de la anorexia nerviosa en adolescentes?",
      "alternativas": [
        {
          "opcion": "A",
          "texto": "Hipertiroidismo"
        },
        {
          "opcion": "B",
          "texto": "Hipocalemia"
        },
        {
          "opcion": "C",
          "texto": "Bradicardia y amenorrea"
        },
        {
          "opcion": "D",
          "texto": "Hiperglicemia"
        },
        {
          "opcion": "E",
          "texto": "Hipertensión"
        }
      ],
      "respuesta_correcta": "C",
      "explicacion": "La desnutrición causa bradicardia, hipotensión, amenorrea y alteraciones hormonales significativas."
    },
    {
      "numero": "3",
      "texto": "¿Cuál de los siguientes trastornos se caracteriza por episodios de ingesta excesiva seguidos de conductas compensatorias?",
      "alternativas": [
        {
          "opcion": "A",
          "texto": "Bulimia nerviosa"
        },
        {
          "opcion": "B",
          "texto": "Anorexia restrictiva"
        },
        {
          "opcion": "C",
          "texto": "Pica"
        },
        {
          "opcion": "D",
          "texto": "Rumicación"
        },
        {
          "opcion": "E",
          "texto": "Trastorno evitativo"
        }
      ],
      "respuesta_correcta": "A",
      "explicacion": "La bulimia nerviosa incluye episodios de atracones con vómito o uso de laxantes como conductas compensatorias."
    },
    {
      "numero": "4",
      "texto": "¿Cuál es el criterio diagnóstico esencial del trastorno por atracón?",
      "alternativas": [
        {
          "opcion": "A",
          "texto": "Restricción calórica"
        },
        {
          "opcion": "B",
          "texto": "Atracones sin conductas compensatorias"
        },
        {
          "opcion": "C",
          "texto": "Pérdida de peso significativa"
        },
        {
          "opcion": "D",
          "texto": "Ejercicio excesivo"
        },
        {
          "opcion": "E",
          "texto": "Amenorrea secundaria"
        }
      ],
      "respuesta_correcta": "B",
      "explicacion": "El trastorno por atracón implica ingestas excesivas sin conductas compensatorias como vómito o ayuno posterior."
    },
    {
      "numero": "5",
      "texto": "¿Qué signo físico es característico de la bulimia nerviosa?",
      "alternativas": [
        {
          "opcion": "A",
          "texto": "Lanugo"
        },
        {
          "opcion": "B",
          "texto": "Hipertrofia de glándulas parótidas"
        },
        {
          "opcion": "C",
          "texto": "Piel seca y fría"
        },
        {
          "opcion": "D",
          "texto": "Edema maleolar"
        },
        {
          "opcion": "E",
          "texto": "Amenorrea primaria"
        }
      ],
      "respuesta_correcta": "B",
      "explicacion": "El vómito repetido produce hipertrofia de las glándulas parótidas y erosión dental."
    },
    {
      "numero": "6",
      "texto": "¿Cuál es la alteración electrolítica más frecuente en bulimia nerviosa con vómitos recurrentes?",
      "alternativas": [
        {
          "opcion": "A",
          "texto": "Hipercalemia"
        },
        {
          "opcion": "B",
          "texto": "Hipocalcemia"
        },
        {
          "opcion": "C",
          "texto": "Hipokalemia"
        },
        {
          "opcion": "D",
          "texto": "Hiponatremia"
        },
        {
          "opcion": "E",
          "texto": "Hiperfosfatemia"
        }
      ],
      "respuesta_correcta": "C",
      "explicacion": "La pérdida de potasio por vómitos o laxantes genera hipokalemia, aumentando el riesgo de arritmias."
    },
    {
      "numero": "7",
      "texto": "¿Qué diagnóstico debe sospecharse ante un niño que consume sustancias no nutritivas de forma persistente?",
      "alternativas": [
        {
          "opcion": "A",
          "texto": "Pica"
        },
        {
          "opcion": "B",
          "texto": "Rumicación"
        },
        {
          "opcion": "C",
          "texto": "Bulimia nerviosa"
        },
        {
          "opcion": "D",
          "texto": "Trastorno evitativo"
        },
        {
          "opcion": "E",
          "texto": "Anorexia nerviosa"
        }
      ],
      "respuesta_correcta": "A",
      "explicacion": "La pica consiste en el consumo persistente de sustancias no alimenticias como tierra o papel."
    },
    {
      "numero": "8",
      "texto": "¿Qué complicación gastrointestinal puede observarse en pacientes con bulimia nerviosa?",
      "alternativas": [
        {
          "opcion": "A",
          "texto": "Esofagitis y desgarro de Mallory-Weiss"
        },
        {
          "opcion": "B",
          "texto": "Intolerancia a la lactosa"
        },
        {
          "opcion": "C",
          "texto": "Enfermedad celíaca"
        },
        {
          "opcion": "D",
          "texto": "Síndrome de intestino irritable"
        },
        {
          "opcion": "E",
          "texto": "Apendicitis"
        }
      ],
      "respuesta_correcta": "A",
      "explicacion": "El vómito repetido puede causar desgarros mucosos esofágicos y esofagitis por reflujo ácido."
    },
    {
      "numero": "9",
      "texto": "¿Cuál de los siguientes es un signo clínico de anorexia nerviosa?",
      "alternativas": [
        {
          "opcion": "A",
          "texto": "Taquicardia"
        },
        {
          "opcion": "B",
          "texto": "Hipertensión arterial"
        },
        {
          "opcion": "C",
          "texto": "Lanugo y piel seca"
        },
        {
          "opcion": "D",
          "texto": "Obesidad central"
        },
        {
          "opcion": "E",
          "texto": "Hiperactividad psicomotora"
        }
      ],
      "respuesta_correcta": "C",
      "explicacion": "La desnutrición severa genera lanugo, piel seca y bradicardia como mecanismos adaptativos."
    },
    {
      "numero": "10",
      "texto": "¿Cuál de los siguientes tratamientos es más efectivo para la anorexia nerviosa?",
      "alternativas": [
        {
          "opcion": "A",
          "texto": "ISRS como monoterapia"
        },
        {
          "opcion": "B",
          "texto": "Terapia familiar y restauración nutricional"
        },
        {
          "opcion": "C",
          "texto": "Benzodiacepinas de acción corta"
        },
        {
          "opcion": "D",
          "texto": "Antipsicóticos atípicos"
        },
        {
          "opcion": "E",
          "texto": "Terapia electroconvulsiva"
        }
      ],
      "respuesta_correcta": "B",
      "explicacion": "El enfoque multidisciplinario con restauración nutricional y terapia familiar es el tratamiento principal."
    },
    {
      "numero": "11",
      "texto": "¿Qué característica diferencia la anorexia nerviosa tipo restrictiva de la purgativa?",
      "alternativas": [
        {
          "opcion": "A",
          "texto": "Presencia de atracones y conductas compensatorias"
        },
        {
          "opcion": "B",
          "texto": "Bajo peso extremo"
        },
        {
          "opcion": "C",
          "texto": "Amenorrea secundaria"
        },
        {
          "opcion": "D",
          "texto": "Ansiedad generalizada"
        },
        {
          "opcion": "E",
          "texto": "Déficit de autoestima"
        }
      ],
      "respuesta_correcta": "A",
      "explicacion": "La forma purgativa incluye atracones y conductas de purga; la restrictiva se basa solo en restricción alimentaria."
    },
    {
      "numero": "12",
      "texto": "¿Qué hallazgo endocrino puede verse en pacientes con anorexia nerviosa?",
      "alternativas": [
        {
          "opcion": "A",
          "texto": "Aumento de T3 y T4"
        },
        {
          "opcion": "B",
          "texto": "Elevación de LH y FSH"
        },
        {
          "opcion": "C",
          "texto": "Disminución de leptina y gonadotropinas"
        },
        {
          "opcion": "D",
          "texto": "Hiperprolactinemia"
        },
        {
          "opcion": "E",
          "texto": "Hipercortisolemia leve"
        }
      ],
      "respuesta_correcta": "C",
      "explicacion": "La desnutrición suprime el eje hipotalámico con disminución de leptina, LH y FSH."
    },
    {
      "numero": "13",
      "texto": "¿Cuál de los siguientes trastornos alimentarios se asocia con re-masticación repetida sin náusea ni enfermedad gastrointestinal?",
      "alternativas": [
        {
          "opcion": "A",
          "texto": "Pica"
        },
        {
          "opcion": "B",
          "texto": "Rumicación"
        },
        {
          "opcion": "C",
          "texto": "Bulimia nerviosa"
        },
        {
          "opcion": "D",
          "texto": "Trastorno por atracón"
        },
        {
          "opcion": "E",
          "texto": "Anorexia nerviosa"
        }
      ],
      "respuesta_correcta": "B",
      "explicacion": "La rumicación implica regurgitación voluntaria y remasticación sin causa médica aparente."
    },
    {
      "numero": "14",
      "texto": "¿Cuál es el principal objetivo terapéutico en un paciente pediátrico con anorexia nerviosa?",
      "alternativas": [
        {
          "opcion": "A",
          "texto": "Eliminar los vómitos"
        },
        {
          "opcion": "B",
          "texto": "Restablecer el peso corporal saludable"
        },
        {
          "opcion": "C",
          "texto": "Reducir la ansiedad social"
        },
        {
          "opcion": "D",
          "texto": "Tratar los síntomas depresivos"
        },
        {
          "opcion": "E",
          "texto": "Aumentar el rendimiento escolar"
        }
      ],
      "respuesta_correcta": "B",
      "explicacion": "El objetivo inicial es restablecer el peso corporal y la nutrición adecuada antes de abordar aspectos psicológicos."
    },
    {
      "numero": "15",
      "texto": "¿Qué trastorno alimentario puede presentarse en niños con autismo o ansiedad ante alimentos nuevos?",
      "alternativas": [
        {
          "opcion": "A",
          "texto": "Anorexia nerviosa"
        },
        {
          "opcion": "B",
          "texto": "Trastorno evitativo/restrictivo de la ingesta alimentaria"
        },
        {
          "opcion": "C",
          "texto": "Pica"
        },
        {
          "opcion": "D",
          "texto": "Bulimia nerviosa"
        },
        {
          "opcion": "E",
          "texto": "Rumicación"
        }
      ],
      "respuesta_correcta": "B",
      "explicacion": "El trastorno evitativo/restrictivo ocurre en niños con miedo o repulsión a ciertos alimentos sin distorsión corporal."
    },
    {
      "numero": "16",
      "texto": "¿Qué hallazgo es común en pacientes con trastorno por atracón?",
      "alternativas": [
        {
          "opcion": "A",
          "texto": "Peso corporal normal o elevado"
        },
        {
          "opcion": "B",
          "texto": "Amenorrea secundaria"
        },
        {
          "opcion": "C",
          "texto": "Hipotermia"
        },
        {
          "opcion": "D",
          "texto": "Hiperactividad física"
        },
        {
          "opcion": "E",
          "texto": "Deficiencia proteica severa"
        }
      ],
      "respuesta_correcta": "A",
      "explicacion": "El trastorno por atracón se asocia a sobrepeso u obesidad debido a la ingesta calórica excesiva sin purga."
    },
    {
      "numero": "17",
      "texto": "¿Qué signo cutáneo puede observarse en pacientes con vómitos autoinducidos crónicos?",
      "alternativas": [
        {
          "opcion": "A",
          "texto": "Acné severo"
        },
        {
          "opcion": "B",
          "texto": "Dermatitis seborreica"
        },
        {
          "opcion": "C",
          "texto": "Callosidades en dorso de la mano (signo de Russell)"
        },
        {
          "opcion": "D",
          "texto": "Equimosis generalizadas"
        },
        {
          "opcion": "E",
          "texto": "Hiperpigmentación en cuello"
        }
      ],
      "respuesta_correcta": "C",
      "explicacion": "El signo de Russell aparece por fricción repetida del dorso de la mano contra los dientes al inducir el vómito."
    },
    {
      "numero": "18",
      "texto": "¿Qué complicación cardiovascular puede aparecer en la anorexia nerviosa?",
      "alternativas": [
        {
          "opcion": "A",
          "texto": "Arritmias por hipokalemia"
        },
        {
          "opcion": "B",
          "texto": "Hipertrofia ventricular izquierda"
        },
        {
          "opcion": "C",
          "texto": "Cardiomegalia"
        },
        {
          "opcion": "D",
          "texto": "Hipertensión pulmonar"
        },
        {
          "opcion": "E",
          "texto": "Soplo funcional sistólico"
        }
      ],
      "respuesta_correcta": "A",
      "explicacion": "Las arritmias, especialmente por hipokalemia y bradicardia, son complicaciones graves en la anorexia nerviosa."
    },
    {
      "numero": "19",
      "texto": "¿Cuál es la actitud médica adecuada ante sospecha de trastorno alimentario en un adolescente?",
      "alternativas": [
        {
          "opcion": "A",
          "texto": "Esperar confirmación familiar antes de actuar"
        },
        {
          "opcion": "B",
          "texto": "Confrontar de forma empática y derivar a equipo multidisciplinario"
        },
        {
          "opcion": "C",
          "texto": "Regañar al paciente para que coma más"
        },
        {
          "opcion": "D",
          "texto": "Iniciar antidepresivos de inmediato"
        },
        {
          "opcion": "E",
          "texto": "Evitar hablar del peso corporal"
        }
      ],
      "respuesta_correcta": "B",
      "explicacion": "La detección temprana y la intervención empática con un equipo multidisciplinario son esenciales para el manejo adecuado."
    }
  ]
}